<document xml:lang="nno" id="no_id">
  <header>
    <title>321 gieldda ožžot ruhtadoarjaga kultuvrralaš vázzinsoappis jagi 2012 - regjeringen.no</title>
    <genre code="admin"/>
    <author>
      <person firstname="" lastname="Kulturdepartementet" sex="unknown" born="" nationality=""/>
    </author>
    <year>2012</year>
    <publChannel>
      <publication>
        <publisher>regjeringen.no</publisher>
      </publication>
    </publChannel>
    <wordcount>1554</wordcount>
    <conversion_status type="standard"/>
    <availability>
      <free/>
    </availability>
    <submitter name="" email="divvun@samediggi.no"/>
    <multilingual/>
    <origFileName>http://regjeringen.no/nn/dep/kud/pressesenter/pressemeldingar/2012/321-kommunar-far-tilskot-til-den-kulture.html?id=705157</origFileName>
    <parallel_text xml:lang="sme" location="bajilgovva-das-mot-raehus-uovvola-on-eam_id_705161.html"/>
    <metadata>
      <uncomplete/>
    </metadata>
    <version>XSLtemplate $Revision: 64438 $; file-specific xsl  Revision; common.xsl  $Revision: 154948 $; </version>
  </header>
  <body>
    <p>321 kommunar får tilskot til Den kulturelle spaserstokken i 2012 - regjeringen.no</p>
    <p>Kulturdepartementet har bestemt at 321 kommunar får midlar frå Den kulturelle spaserstokken i år. I statsbudsjettet for 2012 var det på budsjetta til Kulturdepartementet og Helse- og omsorgsdepartementet løyvd i alt 29,7 millionar kroner til Den kulturelle spaserstokken. Av dette går 1 million kroner til Pensjonistforbundet sitt arbeid med kultur for eldre.</p>
    <p>Midlane til Den kulturelle spaserstokken blir delt ut etter søknad frå kommunane. Nokre kommunar får midlar til samarbeidsprosjekt som omfattar fleire kommunar. Tilskotsbrev blir sendt ut i løpet av hausten.</p>
    <p>Den kulturelle spaserstokken medverker til at eldre menneske får eit profesjonelt kulturtilbod. Den kulturelle spaserstokken stimulerer til samarbeid mellom kultursektoren og omsorgssektoren i kommunane slik at eldre får kulturtilbod i nærmiljøet.</p>
    <p xml:lang="nob">
      <em type="italic">Østfold totalt kr 1 050 000 </em>
    </p>
    <p xml:lang="nob">Moss 180 000 kr Aremark 25 000 kr Sarpsborg 200 000 kr Fredrikstad 200 000 kr Askim 130 000 kr Marker 30 000 kr Hvaler 35 000 kr Rakkestad 5 000 kr Skiptvedt 40 000 kr Hobøl 40 000 kr Halden 90 000 kr Våler 15 000 kr Spydeberg 25 000 kr Rygge 35 000 kr</p>
    <p xml:lang="nob">
      <em type="italic">Akershus totalt kr 2 005 000 </em>
    </p>
    <p xml:lang="isl">Bærum 235 000 kr</p>
    <p>Hurdal 15 000 kr</p>
    <p xml:lang="nob">Asker 200 000 kr</p>
    <p xml:lang="nob">Lørenskog 160 000 kr</p>
    <p xml:lang="nob">Skedsmo 180 000 kr</p>
    <p xml:lang="nob">Aurskog-Høland 50 000 kr</p>
    <p xml:lang="nob">Sørum 220 000 kr</p>
    <p xml:lang="nob">Enebakk 50 000 kr</p>
    <p xml:lang="nob">Ås 15 000 kr</p>
    <p xml:lang="nob">Ski 55 000 kr</p>
    <p xml:lang="nob">Gjerdrum 85 000 kr</p>
    <p xml:lang="nob">Eidsvoll 25 000 kr</p>
    <p xml:lang="nob">Frogn 25 000 kr</p>
    <p xml:lang="nob">Nesodden 165 000 kr</p>
    <p xml:lang="nob">Ullensaker 125 000 kr</p>
    <p xml:lang="nob">Nes i Akershus 140 000 kr</p>
    <p xml:lang="nob">Nittedal 150 000 kr</p>
    <p xml:lang="nob">Vestby 30 000 kr</p>
    <p xml:lang="nob">Rælingen 80 000 kr</p>
    <p>
      <em type="italic">Oslo totalt kr 800 000 </em>
    </p>
    <p>Oslo 800 000 kr</p>
    <p xml:lang="nob">
      <em type="italic">Hedmark totalt kr 1 615 000 </em>
    </p>
    <p xml:lang="nob">Kongsvinger 165 000 kr</p>
    <p xml:lang="nob">Hamar 220 000 kr</p>
    <p xml:lang="nob">Grue 80 000 kr</p>
    <p xml:lang="nob">Ringsaker 180 000 kr</p>
    <p xml:lang="nob">Åsnes 70 000 kr</p>
    <p xml:lang="nob">Elverum 300 000 kr</p>
    <p>Os i Østerdalen 90 000 kr</p>
    <p xml:lang="nob">Nord-Odal 30 000 kr</p>
    <p xml:lang="nob">Alvdal 80 000 kr</p>
    <p>Stor - Elvdal 35 000 kr</p>
    <p>Rendalen 45 000 kr</p>
    <p xml:lang="nob">Trysil 35 000 kr</p>
    <p xml:lang="nob">Stange 110 000 kr</p>
    <p xml:lang="nob">Løten 100 000 kr</p>
    <p xml:lang="nob">Eidskog 10 000 kr</p>
    <p xml:lang="nob">Folldal 15 000 kr</p>
    <p xml:lang="nob">Engerdal 50 000 kr</p>
    <p>
      <em type="italic">Oppland totalt kr 1 695 000 </em>
    </p>
    <p xml:lang="nob">Lillehammer 260 000 kr</p>
    <p>Lesja 30 000 kr</p>
    <p xml:lang="nob">Gjøvik 90 000 kr</p>
    <p>Gran 170 000 kr</p>
    <p>Sel 100 000 kr</p>
    <p>Skjåk 75 000 kr</p>
    <p xml:lang="nob">Østre Toten 105 000 kr</p>
    <p>Dovre 45 000 kr</p>
    <p xml:lang="nob">Øyer 85 000 kr</p>
    <p xml:lang="nob">Vestre Toten 150 000 kr</p>
    <p xml:lang="nob">Nordre Land 40 000 kr</p>
    <p>Øystre Slidre 60 000 kr</p>
    <p xml:lang="nob">Søndre land 35 000 kr</p>
    <p>Nord-Aurdal 35 000 kr</p>
    <p>Sør-Aurdal 45 000 kr</p>
    <p>Vågå 25 000 kr</p>
    <p>Gausdal 90 000 kr</p>
    <p>Lom 20 000 kr</p>
    <p>Etnedal 40 000 kr</p>
    <p>Sør-Fron 25 000 kr</p>
    <p>Nord-Fron 50 000 kr</p>
    <p>Vang 50 000 kr</p>
    <p>Ringebu 70 000 kr</p>
    <p xml:lang="nob">
      <em type="italic">Buskerud totalt kr 2 210 000 </em>
    </p>
    <p xml:lang="nob">Drammen 250 000 kr</p>
    <p xml:lang="nob">Kongsberg mfl 1 000 000 kr</p>
    <p xml:lang="nob">Lier 160 000 kr</p>
    <p xml:lang="nob">Hole 160 000 kr</p>
    <p xml:lang="nob">Nes i Buskerud 0 kr</p>
    <p>Hemsedal 25 000 kr</p>
    <p xml:lang="nob">Nedre Eiker 140 000 kr</p>
    <p xml:lang="nob">Røyken 140 000 kr</p>
    <p>Hol 50 000 kr</p>
    <p>Ål 85 000 kr</p>
    <p>Gol 25 000 kr</p>
    <p xml:lang="isl">Hurum 95 000 kr</p>
    <p xml:lang="nob">Øvre Eiker 80 000 kr</p>
    <p xml:lang="nob">
      <em type="italic">Vestfold totalt kr 1 345 000 </em>
    </p>
    <p xml:lang="nob">Horten 195 000 kr</p>
    <p xml:lang="nob">Sandefjord 155 000 kr</p>
    <p xml:lang="nob">Holmestrand 350 000 kr</p>
    <p xml:lang="nob">Stokke 100 000 kr</p>
    <p>Lardal 25 000 kr</p>
    <p xml:lang="nob">Nøtterøy 120 000 kr</p>
    <p>Sande 95 000 kr</p>
    <p>Svelvik 100 000 kr</p>
    <p xml:lang="nob">Tjøme 25 000 kr</p>
    <p xml:lang="nob">Larvik 180 000 kr</p>
    <p>
      <em type="italic">Telemark totalt kr 1 075 000 </em>
    </p>
    <p xml:lang="nob">Porsgrunn 280 000 kr</p>
    <p xml:lang="nob">Skien 160 000 kr</p>
    <p>Vinje 60 000 kr</p>
    <p xml:lang="nob">Bamble 45 000 kr</p>
    <p>Nome 80 000 kr</p>
    <p xml:lang="nob">Kragerø 50 000 kr</p>
    <p>Bø 150 000 kr</p>
    <p>Tokke 55 000 kr</p>
    <p xml:lang="vep">Siljan 25 000 kr</p>
    <p xml:lang="nob">Drangedal 80 000 kr</p>
    <p>Seljord 90 000 kr</p>
    <p>
      <em type="italic">Aust-Agder totalt kr 565 000 </em>
    </p>
    <p>Grimstad 180 000 kr</p>
    <p xml:lang="nob">Lillesand 65 000 kr</p>
    <p xml:lang="nob">Birkenes 95 000 kr</p>
    <p xml:lang="nob">Arendal 220 000 kr</p>
    <p>Gjerstad 5 000 kr</p>
    <p xml:lang="nob">
      <em type="italic">Vest-Agder totalt kr 1 188 000 </em>
    </p>
    <p xml:lang="nob">Kristiansand 570 000 kr</p>
    <p xml:lang="nob">Valle 30 000 kr</p>
    <p xml:lang="nob">Åseral 25 000 kr</p>
    <p>Audnedal 13 000 kr</p>
    <p xml:lang="nob">Søgne 45 000 kr</p>
    <p>Flekkefjord 80 000 kr</p>
    <p xml:lang="nob">Vennesla 100 000 kr</p>
    <p>Mandal 30 000 kr</p>
    <p>Kvinesdal 25 000 kr</p>
    <p>Sirdal 20 000 kr</p>
    <p>Lindesnes 80 000 kr</p>
    <p xml:lang="nob">Songdalen 60 000 kr</p>
    <p>Lyngdal 50 000 kr</p>
    <p>Hægebostad 20 000 kr</p>
    <p>Farsund 40 000 kr</p>
    <p>
      <em type="italic">Rogaland totalt kr 2 246 000 </em>
    </p>
    <p xml:lang="deu">Haugesund 290 000 kr</p>
    <p>Klepp 100 000 kr</p>
    <p>Time 125 000 kr</p>
    <p>Hå 95 000 kr</p>
    <p xml:lang="deu">Lund 40 000 kr</p>
    <p>Karmøy 220 000 kr</p>
    <p xml:lang="nob">Stavanger 400 000 kr</p>
    <p>Gjesdal 70 000 kr</p>
    <p>Sandnes 200 000 kr</p>
    <p>Suldal 95 000 kr</p>
    <p>Vindafjord 100 000 kr</p>
    <p xml:lang="deu">Eigersund 45 000 kr</p>
    <p>Sokndal 45 000 kr</p>
    <p>Utsira 6 000 kr</p>
    <p>Bjerkreim 5 000 kr</p>
    <p>Sola 45 000 kr</p>
    <p>Sauda 135 000 kr</p>
    <p>Randaberg 60 000 kr</p>
    <p>Hjelmeland 80 000 kr</p>
    <p>Tysvær 90 000 kr</p>
    <p>
      <em type="italic">Hordaland totalt kr 2 405 000 </em>
    </p>
    <p xml:lang="deu">Bergen 655 000 kr</p>
    <p>Øygarden 60 000 kr</p>
    <p>Kvinnherad 110 000 kr</p>
    <p>Voss 95 000 kr</p>
    <p>Austrheim 60 000 kr</p>
    <p>Kvam herad 170 000 kr</p>
    <p>Os 145 000 kr</p>
    <p>Askøy 170 000 kr</p>
    <p>Osterøy 120 000 kr</p>
    <p>Lindås 105 000 kr</p>
    <p xml:lang="sms">Odda 35 000 kr</p>
    <p>Ullensvang herad 80 000 kr</p>
    <p>Fedje 10 000 kr</p>
    <p>Austevoll 45 000 kr</p>
    <p>Granvin Herad 30 000 kr</p>
    <p xml:lang="deu">Sund 60 000 kr</p>
    <p>Fusa 45 000 kr</p>
    <p>Masfjorden 20 000 kr</p>
    <p>Radøy 35 000 kr</p>
    <p>Tysnes 15 000 kr</p>
    <p>Ulvik 25 000 kr</p>
    <p>Meland 40 000 kr</p>
    <p>Stord 60 000 kr</p>
    <p>Jondal 25 000 kr</p>
    <p>Eidfjord 10 000 kr</p>
    <p>Bømlo 140 000 kr</p>
    <p>Samnanger 40 000 kr</p>
    <p>
      <em type="italic">Sogn og Fjordane totalt kr 1 300 000 </em>
    </p>
    <p>Førde 95 000 kr</p>
    <p>Fjaler 95 000 kr</p>
    <p>Balestrand 5 000 kr</p>
    <p>Jølster 45 000 kr</p>
    <p>Gaular 55 000 kr</p>
    <p>Selje 35 000 kr</p>
    <p>Vågsøy 60 000 kr</p>
    <p>Vik 25 000 kr</p>
    <p>Sogndal 35 000 kr</p>
    <p>Naustdal 70 000 kr</p>
    <p>Stryn 90 000 kr</p>
    <p>Høyanger 40 000 kr</p>
    <p>Eid 95 000 kr</p>
    <p>Hyllestad 90 000 kr</p>
    <p>Flora 95 000 kr</p>
    <p>Leikanger 20 000 kr</p>
    <p>Gloppen 45 000 kr</p>
    <p>Luster 60 000 kr</p>
    <p>Askvoll 60 000 kr</p>
    <p>Årdal 25 000 kr</p>
    <p xml:lang="deu">Solund 40 000 kr</p>
    <p>Hornindal 100 000 kr</p>
    <p>Lærdal 20 000 kr</p>
    <p>
      <em type="italic">Møre og Romsdal totalt kr 1 950 000 </em>
    </p>
    <p>Halsa 60 000 kr</p>
    <p>Ørsta 60 000 kr</p>
    <p>Averøy 30 000 kr</p>
    <p>Herøy 75 000 kr</p>
    <p>Ålesund 270 000 kr</p>
    <p>Hareid 65 000 kr</p>
    <p xml:lang="est">Volda 190 000 kr</p>
    <p>Sula 75 000 kr</p>
    <p>Giske 100 000 kr</p>
    <p>Haram 100 000 kr</p>
    <p>Sande 35 000 kr</p>
    <p>Gjemnes 50 000 kr</p>
    <p xml:lang="nob">Rindal 50 000 kr</p>
    <p>Ulstein 100 000 kr</p>
    <p>Fræna 55 000 kr</p>
    <p>Norddal 60 000 kr</p>
    <p>Stordal 60 000 kr</p>
    <p>Ørskog 20 000 kr</p>
    <p>Nesset 55 000 kr</p>
    <p>Skodje 25 000 kr</p>
    <p xml:lang="nob">Vestnes 40 000 kr</p>
    <p>Molde 100 000 kr</p>
    <p>Kristiansund 130 000 kr</p>
    <p>Vanylven 45 000 kr</p>
    <p>Aure 80 000 kr</p>
    <p>Tingvoll 20 000 kr</p>
    <p xml:lang="nob">
      <em type="italic">Sør-Trøndelag totalt kr 1 455 000 </em>
    </p>
    <p xml:lang="nob">Trondheim 450 000 kr</p>
    <p>Agdenes 15 000 kr</p>
    <p xml:lang="kal">Rissa 30 000 kr</p>
    <p>Hemne 25 000 kr</p>
    <p>Åfjord 100 000 kr</p>
    <p>Oppdal 5 000 kr</p>
    <p>Orkdal 45 000 kr</p>
    <p xml:lang="nob">Osen 20 000 kr</p>
    <p xml:lang="nob">Røros 50 000 kr</p>
    <p>Selbu 45 000 kr</p>
    <p>Holtålen 40 000 kr</p>
    <p xml:lang="nob">Klæbu 20 000 kr</p>
    <p xml:lang="nob">Ørland 90 000 kr</p>
    <p>Midtre Gauldal 140 000 kr</p>
    <p>Skaun 5 000 kr</p>
    <p xml:lang="nob">Malvik 85 000 kr</p>
    <p xml:lang="nob">Hitra 45 000 kr</p>
    <p xml:lang="nob">Meldal 20 000 kr</p>
    <p>Bjugn 60 000 kr</p>
    <p>Frøya 35 000 kr</p>
    <p>Rennebu 20 000 kr</p>
    <p xml:lang="nob">Tydal 20 000 kr</p>
    <p xml:lang="nob">Melhus 75 000 kr</p>
    <p xml:lang="nob">Roan 15 000 kr</p>
    <p xml:lang="nob">
      <em type="italic">Nord-Trøndelag totalt kr 1 293 000 </em>
    </p>
    <p>Steinkjer 295 000 kr</p>
    <p xml:lang="nob">Stjørdal 150 000 kr</p>
    <p xml:lang="nob">Levanger 180 000 kr</p>
    <p>Verdal 45 000 kr</p>
    <p>Namdalseid 60 000 kr</p>
    <p xml:lang="nob">Snåsa 60 000 kr</p>
    <p>Namsskogan 23 000 kr</p>
    <p xml:lang="nob">Grong 60 000 kr</p>
    <p>Vikna 25 000 kr</p>
    <p xml:lang="vep">Verran 20 000 kr</p>
    <p>Meråker 20 000 kr</p>
    <p>Frosta 50 000 kr</p>
    <p xml:lang="nob">Overhalla 30 000 kr</p>
    <p xml:lang="nob">Namsos 70 000 kr</p>
    <p xml:lang="nob">Inderøy 90 000 kr</p>
    <p xml:lang="nob">Lierne 40 000 kr</p>
    <p>Fosnes 25 000 kr</p>
    <p>Nærøy 50 000 kr</p>
    <p>
      <em type="italic">Nordland totalt kr 2 055 000 </em>
    </p>
    <p xml:lang="nob">Bodø 200 000 kr</p>
    <p>Fauske 350 000 kr</p>
    <p xml:lang="nob">Narvik 195 000 kr</p>
    <p>Sortland 100 000 kr</p>
    <p>Brønnøy 160 000 kr</p>
    <p>Steigen 0 kr</p>
    <p>Hemnes 15 000 kr</p>
    <p>Vestvågøy 95 000 kr</p>
    <p>Bø i Vesterålen 90 000 kr</p>
    <p>Vega 80 000 kr</p>
    <p>Grane 50 000 kr</p>
    <p>Lødingen 30 000 kr</p>
    <p>Tjeldsund 20 000 kr</p>
    <p>Flakstad 20 000 kr</p>
    <p>Andøy 60 000 kr</p>
    <p xml:lang="nob">Evenes 25 000 kr</p>
    <p>Værøy 20 000 kr</p>
    <p>Vågan 200 000 kr</p>
    <p xml:lang="nob">Rana 100 000 kr</p>
    <p>Alstahaug 20 000 kr</p>
    <p>Nesna 80 000 kr</p>
    <p>Vefsn 60 000 kr</p>
    <p>Rødøy 10 000 kr</p>
    <p>Hadsel 50 000 kr</p>
    <p>Øksnes 25 000 kr</p>
    <p xml:lang="nob">
      <em type="italic">Troms totalt kr 1 483 000 </em>
    </p>
    <p xml:lang="nob">Tromsø 500 000 kr</p>
    <p>Tranøy 25 000 kr</p>
    <p>Målselv 75 000 kr</p>
    <p xml:lang="nob">Harstad 330 000 kr</p>
    <p xml:lang="nob">Sørreisa 65 000 kr</p>
    <p>Gratangen 45 000 kr</p>
    <p xml:lang="nob">Balsfjord 25 000 kr</p>
    <p>Storfjord 75 000 kr</p>
    <p xml:lang="nob">Lyngen 95 000 kr</p>
    <p>Bjarkøy 10 000 kr</p>
    <p>Bardu 60 000 kr</p>
    <p>Lenvik 75 000 kr</p>
    <p>Kvæfjord 10 000 kr</p>
    <p>Karlsøy 8 000 kr</p>
    <p>Torsken 25 000 kr</p>
    <p>Salangen 60 000 kr</p>
    <p>Ibestad 35 000 kr</p>
    <p xml:lang="nob">
      <em type="italic">Finnmark totalt kr 1 015 000 </em>
    </p>
    <p xml:lang="nob">Hammerfest 95 000 kr</p>
    <p>Gamvik 25 000 kr</p>
    <p>Båtsfjord 15 000 kr</p>
    <p xml:lang="nob">Alta 200 000 kr</p>
    <p>Måsøy 100 000 kr</p>
    <p xml:lang="nob">Lebesby 80 000 kr</p>
    <p xml:lang="nob">Sør-Varanger 150 000 kr</p>
    <p>Nordkapp 80 000 kr</p>
    <p xml:lang="nob">Loppa 15 000 kr</p>
    <p xml:lang="nob">Porsanger 50 000 kr</p>
    <p xml:lang="nob">Berlevåg 20 000 kr</p>
    <p xml:lang="nob">Vadsø 30 000 kr</p>
    <p xml:lang="est">Kvalsund 30 000 kr</p>
    <p xml:lang="nob">Tana 75 000 kr</p>
    <p xml:lang="nob">Karasjok 50 000 kr</p>
  </body>
</document>
