<document xml:lang="nno" id="no_id">
  <header>
    <title>Stáhtačálli Lars Erik Bartnes - regjeringen.no</title>
    <genre code="admin"/>
    <author>
      <person firstname="" lastname="Samferdselsdepartementet" sex="unknown" born="" nationality=""/>
    </author>
    <translator>
      <unknown/>
    </translator>
    <translated_from xml:lang="nob"/>
    <year>2009</year>
    <publChannel>
      <publication>
        <publisher>regjeringen.no</publisher>
      </publication>
    </publChannel>
    <wordcount>108</wordcount>
    <conversion_status type="standard"/>
    <availability>
      <free/>
    </availability>
    <submitter name="" email="divvun@samediggi.no"/>
    <origFileName>http://regjeringen.no/nn/dep/sd/om-departementet/anna-politisk-leiing/statssekretar-lars-erik-bartnes.html?id=582289</origFileName>
    <parallel_text xml:lang="eng" location="state-secretary-lars-erik-bartnes_id_582289.html"/>
    <parallel_text xml:lang="nob" location="statssekretar-lars-erik-bartnes_id_582289.html"/>
    <parallel_text xml:lang="sme" location="stahtaalli-lars-erik-bartnes_id_582289.html"/>
    <metadata>
      <uncomplete/>
    </metadata>
    <version>XSLtemplate $Revision$; file-specific xsl  Revision; common.xsl  $Revision: 154948 $; </version>
  </header>
  <body>
    <p>Statssekretær Lars Erik Bartnes - regjeringen.no</p>
    <p>
      <em type="italic">Politiske verv </em>
    </p>
    <p>2009 Statssekretær i Samferdselsdepartementet 2009-2009 Politisk rådgjevar, Kommunal- og regionaldepartementet 2009- Statssekretær, Kommunal- og regionaldepartementet 2007-2009 Politisk rådgjevar, Kommunal- og regionaldepartementet 2003-2004 Styremedlem, Sentralstyret i Senterungdommen 2002-2003 Nestleiar/leiar, Nord-Trønderlag Senterungdom</p>
    <p>
      <em type="italic">Yrkeserfaring </em>
    </p>
    <p>2005-2007 Medierådgjevar for Senterpartiets stortingsgruppe 2004-2005 Studieassistent for ekspertar i team. Norges teknisk-naturvitskaplege Universitet, Trondheim 2000-2001 Nestkommanderande/patruljeførar, tropp 1 Oppklaringsskvadronen, Rena 1999-2000 Patruljeførar, Esk1/Tropp 1 Oppklaringsbataljonen, Sætermoen 1992-2005 Gardsgut, Bartnes</p>
    <p>
      <em type="italic">Utdanning </em>
    </p>
    <p>2004-2005 Masterstudier i statsvitskap, Norges teknisk-naturvitskaplege Universitet, Trondheim 2001-2004 Bachelor i statsvitskap, Norges teknisk-naturvitskaplege Universitet, Trondheim 1998-1999 Befalskulen for kavaleriet, Oppklaringslinja, Rena 1997-1998 Ringebu folkehøgskule, Idrettslinja 1994-1997 Steinkjer videregående skule, Idrettslinja</p>
    <p>
      <em type="italic">Andre verv </em>
    </p>
    <p>1994-1995 Leiar, Fram 4H, Bartnes</p>
  </body>
</document>
